exfinance/__init__.py
exfinance/downloader.py
exfinance-0.1.1.dist-info/LICENSE
exfinance-0.1.1.dist-info/METADATA
exfinance-0.1.1.dist-info/WHEEL
exfinance-0.1.1.dist-info/RECORD
