Metadata-Version: 2.1
Name: exfinance
Version: 0.1.1
Summary: A Python package for downloading financial data from ex2archive
Home-page: https://github.com/alihaskar/efinance
Keywords: finance,data,exness,trading
Author: Ali H. Askar
Author-email: 26202651+alihaskar@users.noreply.github.com
Requires-Python: >=3.11,<4.0
Classifier: Development Status :: 3 - Alpha
Classifier: Intended Audience :: Developers
Classifier: License :: OSI Approved :: MIT License
Classifier: Programming Language :: Python :: 3
Classifier: Programming Language :: Python :: 3.11
Classifier: Programming Language :: Python :: 3.12
Requires-Dist: numpy (>=1.26.4,<2.0.0)
Requires-Dist: pandas (>=2.2.2,<3.0.0)
Project-URL: Repository, https://github.com/alihaskar/efinance
